django_qr_toolkit_core-4.3.2.dist-info/licenses/LICENSE
django_qr_toolkit_models/__init__.py
django_qr_toolkit_models/asgi.py
django_qr_toolkit_models/settings.py
django_qr_toolkit_models/urls.py
django_qr_toolkit_models/wsgi.py
qrtoolkit_core/__init__.py
qrtoolkit_core/admin.py
qrtoolkit_core/apps.py
qrtoolkit_core/models.py
qrtoolkit_core/serializers.py
qrtoolkit_core/tests.py
qrtoolkit_core/urls.py
qrtoolkit_core/validators.py
qrtoolkit_core/views.py
qrtoolkit_core/viewsets.py
qrtoolkit_core/generator/__init__.py
qrtoolkit_core/generator/forms.py
qrtoolkit_core/generator/qr.py
qrtoolkit_core/generator/zip.py
qrtoolkit_core/migrations/0001_initial.py
qrtoolkit_core/migrations/0002_auto_20210202_1257.py
qrtoolkit_core/migrations/0003_department_users.py
qrtoolkit_core/migrations/0004_auto_20210512_0733.py
qrtoolkit_core/migrations/0005_remove_erronous_hits.py
qrtoolkit_core/migrations/0006_auto_20210614_1338.py
qrtoolkit_core/migrations/0007_auto_20210630_1417.py
qrtoolkit_core/migrations/0008_auto_20210630_1526.py
qrtoolkit_core/migrations/0009_linkurl_visible.py
qrtoolkit_core/migrations/0010_auto_20210929_1616.py
qrtoolkit_core/migrations/0011_auto_20220224_1533.py
qrtoolkit_core/migrations/0012_qrcode_kiosk_introduction.py
qrtoolkit_core/migrations/0013_auto_20220822_0754.py
qrtoolkit_core/migrations/0014_alter_apicall_id_alter_apihit_id_alter_department_id_and_more.py
qrtoolkit_core/migrations/0015_alter_apicall_id_alter_apihit_hit_date_and_more.py
qrtoolkit_core/migrations/__init__.py
qrtoolkit_core/static/qrtoolkit_core/css/download.css
qrtoolkit_core/static/qrtoolkit_core/css/kiosk.css
qrtoolkit_core/static/qrtoolkit_core/fonts/gent-icons.eot
qrtoolkit_core/static/qrtoolkit_core/fonts/gent-icons.svg
qrtoolkit_core/static/qrtoolkit_core/fonts/gent-icons.ttf
qrtoolkit_core/static/qrtoolkit_core/fonts/gent-icons.woff
qrtoolkit_core/static/qrtoolkit_core/fonts/gent-icons.woff2
qrtoolkit_core/static/qrtoolkit_core/img/loading.gif
qrtoolkit_core/static/qrtoolkit_core/js/download.form.js
django_qr_toolkit_core-4.3.2.dist-info/METADATA
django_qr_toolkit_core-4.3.2.dist-info/WHEEL
django_qr_toolkit_core-4.3.2.dist-info/top_level.txt
django_qr_toolkit_core-4.3.2.dist-info/RECORD
