Metadata-Version: 2.4
Name: django-qr-toolkit-core
Version: 4.3.2
Summary: A Django app to use qr-toolkit models
Home-page: https://github.com/lab9k/qrtoolkit-core
Author: Willems Jef
Author-email: jef.willems@district09.gent
Classifier: Environment :: Web Environment
Classifier: Framework :: Django
Classifier: Intended Audience :: Developers
Classifier: Operating System :: OS Independent
Classifier: Programming Language :: Python
Classifier: Programming Language :: Python :: 3.6
Classifier: Programming Language :: Python :: 3.7
Classifier: Programming Language :: Python :: 3.8
Classifier: Topic :: Internet :: WWW/HTTP
Classifier: Topic :: Internet :: WWW/HTTP :: Dynamic Content
License-File: LICENSE
Requires-Dist: bleach
Requires-Dist: Django
Requires-Dist: django-filter
Requires-Dist: django-reversion
Requires-Dist: djangorestframework
Requires-Dist: requests
Requires-Dist: segno
Dynamic: license-file
